mongo_broadcaster/__init__.py
mongo_broadcaster/broadcaster.py
mongo_broadcaster/exceptions.py
mongo_broadcaster/models.py
mongo_broadcaster/utils.py
mongo_broadcaster/channels/__init__.py
mongo_broadcaster/channels/base.py
mongo_broadcaster/channels/database.py
mongo_broadcaster/channels/http.py
mongo_broadcaster/channels/redis.py
mongo_broadcaster/channels/websocket.py
mongo_broadcaster/examples/database_example.py
mongo_broadcaster/examples/http_example.py
mongo_broadcaster/examples/redis_example.py
mongo_broadcaster/examples/test_http_server.py
mongo_broadcaster/examples/websocket_example.py
mongo_broadcaster-0.1.6.dist-info/licenses/LICENSE
mongo_broadcaster-0.1.6.dist-info/METADATA
mongo_broadcaster-0.1.6.dist-info/WHEEL
mongo_broadcaster-0.1.6.dist-info/top_level.txt
mongo_broadcaster-0.1.6.dist-info/RECORD
